eisen/__init__.py
eisen/datasets/Brats.py
eisen/datasets/__init__.py
eisen/datasets/abcs.py
eisen/datasets/camelyon.py
eisen/datasets/camus.py
eisen/datasets/emidec_challenge.py
eisen/datasets/json.py
eisen/datasets/kaggle_covid.py
eisen/datasets/med_seg_covid19.py
eisen/datasets/msd.py
eisen/datasets/panda.py
eisen/datasets/rsna_bone_age.py
eisen/datasets/rsna_ihd.py
eisen/datasets/ucsd_cls_covid19.py
eisen/io/__init__.py
eisen/io/imaging.py
eisen/models/__init__.py
eisen/models/segmentation/__init__.py
eisen/models/segmentation/highres3Dnet.py
eisen/models/segmentation/obelisk.py
eisen/models/segmentation/unet.py
eisen/models/segmentation/unet3D.py
eisen/models/segmentation/vnet.py
eisen/ops/__init__.py
eisen/ops/layers/__init__.py
eisen/ops/losses/__init__.py
eisen/ops/losses/dice.py
eisen/ops/metrics/__init__.py
eisen/ops/metrics/dice.py
eisen/transforms/__init__.py
eisen/transforms/imaging.py
eisen/transforms/inspect.py
eisen/utils/__init__.py
eisen/utils/artifacts/__init__.py
eisen/utils/artifacts/savemodel.py
eisen/utils/logging/__init__.py
eisen/utils/logging/logs.py
eisen/utils/logging/summaries.py
eisen/utils/workflows/__init__.py
eisen/utils/workflows/hooks.py
eisen/utils/workflows/testing.py
eisen/utils/workflows/training.py
eisen/utils/workflows/validation.py
eisen/utils/workflows/workflows.py
tests/__init__.py
tests/datasets/__init__.py
tests/datasets/datasets_test.py
tests/io/__init__.py
tests/io/imaging_test.py
tests/transforms/__init__.py
tests/transforms/imaging_test.py
tests/utils/__init__.py
tests/utils/workflows_test.py
eisen_core-0.0.9.dist-info/LICENSE
eisen_core-0.0.9.dist-info/METADATA
eisen_core-0.0.9.dist-info/WHEEL
eisen_core-0.0.9.dist-info/entry_points.txt
eisen_core-0.0.9.dist-info/top_level.txt
eisen_core-0.0.9.dist-info/RECORD
