Metadata-Version: 2.1
Name: eisen-core
Version: 0.0.9
Summary: Eisen is a collection of tools to train neural networks for medical image analysis
Home-page: UNKNOWN
License: UNKNOWN
Platform: UNKNOWN
Requires-Python: >=3.6
Requires-Dist: nilearn (>=0.6.0)
Requires-Dist: torch (>=1.6.0)
Requires-Dist: torchvision (>=0.7.0)
Requires-Dist: numpy (>=1.18.0)
Requires-Dist: nibabel (>=3.0.0)
Requires-Dist: prettytable (>=0.7.2)
Requires-Dist: PyDispatcher (>=2.0.5)
Requires-Dist: h5py (>=2.10.0)
Requires-Dist: tensorboard (>=2.1.1)
Requires-Dist: matplotlib (>=3.0.3)
Requires-Dist: SimpleITK (>=1.2.4)
Requires-Dist: pydicom (>=1.4.2)
Requires-Dist: moviepy (>=1.0.1)
